fiend/__init__.py
fiend/analysis/__init__.py
fiend/analysis/_pes_tsurff.py
fiend/analysis/_unit_conversions.py
fiend/analysis/_visualization_utils.py
fiend/analysis/animate_density.py
fiend/analysis/custom.mplparams
fiend/analysis/draw_acceleration.py
fiend/analysis/draw_dipole.py
fiend/analysis/draw_final_state.py
fiend/analysis/draw_laser.py
fiend/analysis/draw_mesh.py
fiend/analysis/draw_norm.py
fiend/analysis/draw_pes.py
fiend/analysis/draw_snapshot.py
fiend/analysis/draw_stationary_states.py
fiend/analysis/draw_velocity.py
fiend/analysis/tests/__init__.py
fiend/analysis/tests/test_pes_tsurff.py
fiend/lin_pol/__init__.py
fiend/lin_pol/prepare_tdse.py
fiend/lin_pol/propagate.py
fiend/lin_pol/solve_tise.py
fiend/propagation/__init__.py
fiend/propagation/observables.py
fiend/propagation/propagation_utils.py
fiend/propagation/propagators.py
fiend/propagation/tests/__init__.py
fiend/propagation/tests/test_prepare_propagator_tests.py
fiend/propagation/tests/test_propagators.py
fiend/pulseconfig_parser/__init__.py
fiend/pulseconfig_parser/laser.py
fiend/pulseconfig_parser/parameter.py
fiend/pulseconfig_parser/parser.py
fiend/pulseconfig_parser/singlecolorlaserpulse.py
fiend/tdse/__init__.py
fiend/tdse/absorbing_boundaries.py
fiend/tdse/tdse.py
fiend/tdse/tests/__init__.py
fiend/tdse/tests/test_cap.py
fiend/tests/__init__.py
fiend/tests/test_mypy.py
fiend/tise/__init__.py
fiend/tise/tise.py
fiend/tise/tests/__init__.py
fiend/tise/tests/test_tise.py
fiend/utils/__init__.py
fiend/utils/custom_matrices.py
fiend/utils/dolfin.py
fiend/utils/mesh.py
fiend/utils/misc.py
fiend/utils/mpi.py
fiend/utils/petsc_utils.py
fiend/utils/predefined_potentials.py
fiend/utils/tests/__init__.py
fiend/utils/tests/test_custom_matrices.py
fiend/utils/tests/test_dolfin.py
fiend/utils/tests/test_mesh.py
fiend/utils/tests/test_misc.py
fiend/utils/tests/test_potentials.py
fiend-1.0.3.data/data/demos/hhg/laser
fiend-1.0.3.dist-info/METADATA
fiend-1.0.3.dist-info/RECORD
fiend-1.0.3.dist-info/WHEEL
fiend-1.0.3.dist-info/entry_points.txt
fiend-1.0.3.dist-info/top_level.txt
fiend-1.0.3.dist-info/zip-safe
