Metadata-Version: 2.1
Name: fiend
Version: 1.0.3
Summary: Finite element nanoscale dynamics
Home-page: https://fiend.solanpaa.fi
Author: Janne Solanpää
Author-email: janne+fiend@solanpaa.fi
License: MIT License
Keywords: numerics,FEM,finite-element method,quantum mechanics,Schrödinger equation,physics
Platform: UNKNOWN
Classifier: Development Status :: 5 - Production/Stable
Classifier: Environment :: Console
Classifier: Intended Audience :: Science/Research
Classifier: License :: OSI Approved :: MIT License
Classifier: Operating System :: OS Independent
Classifier: Programming Language :: Python :: 3 :: Only
Classifier: Programming Language :: Python :: 3.6
Classifier: Topic :: Scientific/Engineering :: Physics
Requires-Python: >=3.6
Requires-Dist: numpy
Requires-Dist: scipy
Requires-Dist: matplotlib
Requires-Dist: h5py
Requires-Dist: mpi4py
Requires-Dist: petsc4py
Requires-Dist: slepc4py
Requires-Dist: fenics-dolfin
Requires-Dist: mshr
Requires-Dist: psutil
Requires-Dist: progressbar2
Requires-Dist: mypy
